<?xml version="1.0" encoding="utf-8" ?>
<dwsync>
<file name="b motor.JPG" server="02dbcc5.netsolhost.com//greenpedals2016/" local="129781524260000000" remote="131084286130000000" />
<file name="bionx-100w.jpg" server="02dbcc5.netsolhost.com//greenpedals2016/" local="129781524180000000" remote="131084286130000000" />
<file name="bionx-conversion-kits-130w.jpg" server="02dbcc5.netsolhost.com//greenpedals2016/" local="129781524180000000" remote="131084286130000000" />
<file name="bionx-conversion-kits.jpg" server="02dbcc5.netsolhost.com//greenpedals2016/" local="129781524200000000" remote="131084286140000000" />
<file name="bionx-thumb.jpg" server="02dbcc5.netsolhost.com//greenpedals2016/" local="129781524200000000" remote="131084286140000000" />
<file name="bionx.jpg" server="02dbcc5.netsolhost.com//greenpedals2016/" local="129781524200000000" remote="131084286140000000" />
<file name="conversion-kits-100w.jpg" server="02dbcc5.netsolhost.com//greenpedals2016/" local="129781524200000000" remote="131084286140000000" />
<file name="conversion-kits-thumb.jpg" server="02dbcc5.netsolhost.com//greenpedals2016/" local="129781524200000000" remote="131084286140000000" />
<file name="conversion-kits.jpg" server="02dbcc5.netsolhost.com//greenpedals2016/" local="129781524200000000" remote="131084286140000000" />
</dwsync>